uranie_launcher/VERSION
uranie_launcher/__init__.py
uranie_launcher/_data_2_uranie.py
uranie_launcher/_run_unitary.py
uranie_launcher/data.py
uranie_launcher/execution.py
uranie_launcher/input_data.py
uranie_launcher/launcher.py
uranie_launcher/utils.py
uranie_launcher-3.0.1.dist-info/LICENSE
uranie_launcher-3.0.1.dist-info/METADATA
uranie_launcher-3.0.1.dist-info/WHEEL
uranie_launcher-3.0.1.dist-info/entry_points.txt
uranie_launcher-3.0.1.dist-info/top_level.txt
uranie_launcher-3.0.1.dist-info/RECORD
