Metadata-Version: 2.1
Name: uranie-launcher
Version: 3.0.1
Summary: uranie-launcher help you to run your calculation scripts with Uranie
Home-page: UNKNOWN
Author: Clément STUTZ
Author-email: clement.stutz@cea.fr
License: UNKNOWN
Project-URL: Bug Reports, https://github.com/clementstutz/uranie-launcher/issues
Project-URL: Source, https://github.com/clementstutz/uranie-launcher
Platform: UNKNOWN
License-File: LICENSE
Provides-Extra: dev
Requires-Dist: pytest ; extra == 'dev'
